{
	"comment": "Random grid, random settings and the meanest puzzle we could manage in 30 seconds. Difficulty: 2.36, best of 6563 attempts.",
	"grid": "octagonal",
	"width": 11,
	"height": 11,
	"wrap": false,
	"tiles": [
		0,
		0,
		0,
		129,
		80,
		130,
		9,
		192,
		0,
		0,
		0,
		0,
		0,
		160,
		170,
		208,
		144,
		132,
		197,
		10,
		0,
		0,
		0,
		65,
		40,
		192,
		65,
		84,
		5,
		194,
		25,
		4,
		0,
		3,
		66,
		73,
		5,
		44,
		18,
		76,
		160,
		232,
		33,
		10,
		144,
		7,
		21,
		134,
		130,
		0,
		8,
		65,
		18,
		65,
		13,
		130,
		3,
		137,
		100,
		0,
		0,
		0,
		208,
		36,
		13,
		134,
		8,
		9,
		97,
		33,
		20,
		0,
		6,
		194,
		48,
		44,
		48,
		12,
		70,
		33,
		20,
		152,
		138,
		20,
		65,
		88,
		161,
		3,
		0,
		64,
		146,
		106,
		3,
		138,
		12,
		130,
		86,
		64,
		0,
		0,
		0,
		160,
		196,
		82,
		12,
		148,
		20,
		12,
		0,
		0,
		0,
		0,
		0,
		10,
		3,
		66,
		13,
		6,
		0,
		0,
		0,
		0,
		0,
		2,
		10,
		162,
		40,
		8,
		128,
		0,
		0,
		0,
		0,
		160,
		10,
		2,
		136,
		32,
		40,
		130,
		128,
		0,
		0,
		8,
		40,
		40,
		160,
		2,
		160,
		160,
		128,
		160,
		40,
		0,
		130,
		2,
		8,
		32,
		32,
		160,
		40,
		2,
		2,
		130,
		0,
		10,
		128,
		8,
		10,
		0,
		0,
		130,
		160,
		32,
		2,
		0,
		160,
		128,
		34,
		2,
		0,
		0,
		2,
		160,
		128,
		136,
		0,
		162,
		2,
		10,
		10,
		32,
		128,
		10,
		8,
		8,
		160,
		0,
		2,
		160,
		128,
		2,
		160,
		10,
		40,
		34,
		130,
		2,
		0,
		0,
		40,
		10,
		32,
		128,
		40,
		8,
		8,
		160,
		0,
		0,
		0,
		0,
		128,
		10,
		10,
		40,
		128,
		8,
		0,
		0,
		0,
		0,
		0,
		0,
		0,
		0,
		0,
		0,
		0,
		0,
		0,
		0
	]
}